starlette_di/__init__.py
starlette_di/definitions.py
starlette_di/inject.py
starlette_di/middleware.py
starlette_di/service_collection.py
starlette_di/service_provider.py
starlette_di/types.py
starlette_di-0.1.1.dist-info/LICENSE
starlette_di-0.1.1.dist-info/METADATA
starlette_di-0.1.1.dist-info/WHEEL
starlette_di-0.1.1.dist-info/top_level.txt
starlette_di-0.1.1.dist-info/RECORD
