Metadata-Version: 2.2
Name: starlette-di
Version: 0.1.1
Summary: A dependency injection library for Starlette. It supports Scoped, Transient, and Singleton lifetimes, route parameter and request body injection via Pydantic, and seamless integration with Starlette using decorators and middleware.
Author-email: Dairo Mosquera <dairoandres115@outlook.com>
Project-URL: Homepage, https://github.com/daireto/starlette-di
Project-URL: Issues, https://github.com/daireto/starlette-di/issues
Project-URL: Repository, https://github.com/daireto/starlette-di
Keywords: starlette-di,dependency injection,di,starlette,starlette extension,starlette middleware
Classifier: Programming Language :: Python :: 3.10
Classifier: Programming Language :: Python :: 3.11
Classifier: Programming Language :: Python :: 3.12
Classifier: Programming Language :: Python :: 3.13
Classifier: Programming Language :: Python :: 3.14
Classifier: License :: OSI Approved :: MIT License
Classifier: Operating System :: OS Independent
Classifier: Intended Audience :: Developers
Requires-Python: >=3.10
License-File: LICENSE
Requires-Dist: pydantic>=1.10.21
Requires-Dist: starlette>=0.38.0
